fcdocs/__init__.py
fcdocs/__main__.py
fcdocs/cli.py
fcdocs/pipeline_registry.py
fcdocs/settings.py
fcdocs/extras/__init__.py
fcdocs/extras/datasets/__init__.py
fcdocs/extras/datasets/document_dataset.py
fcdocs/pipelines/__init__.py
fcdocs/pipelines/classifier/__init__.py
fcdocs/pipelines/classifier/model_dataset.py
fcdocs/pipelines/classifier/models.py
fcdocs/pipelines/classifier/nodes.py
fcdocs/pipelines/classifier/pipeline.py
fcdocs/pipelines/clustering/__init__.py
fcdocs/pipelines/clustering/model_dataset.py
fcdocs/pipelines/clustering/models.py
fcdocs/pipelines/clustering/nodes.py
fcdocs/pipelines/clustering/pipeline.py
fcdocs/pipelines/data_processing/__init__.py
fcdocs/pipelines/data_processing/nodes.py
fcdocs/pipelines/data_processing/pipeline.py
tests/pipelines/__init__.py
tests/pipelines/classifier/__init__.py
tests/pipelines/classifier/test_pipeline.py
tests/pipelines/clustering/__init__.py
tests/pipelines/clustering/test_pipeline.py
fcdocs-0.2.dist-info/METADATA
fcdocs-0.2.dist-info/WHEEL
fcdocs-0.2.dist-info/entry_points.txt
fcdocs-0.2.dist-info/top_level.txt
fcdocs-0.2.dist-info/RECORD
